repetition/__init__.py
repetition/repetition.py
repetition/white.txt
repetition-1.0.5.dist-info/DESCRIPTION.rst
repetition-1.0.5.dist-info/METADATA
repetition-1.0.5.dist-info/RECORD
repetition-1.0.5.dist-info/WHEEL
repetition-1.0.5.dist-info/metadata.json
repetition-1.0.5.dist-info/top_level.txt
