Metadata-Version: 2.0
Name: repetition
Version: 1.0.5
Summary: remove repetition
Home-page: https://pypi.org/
Author: shaozhuquan
Author-email: shaozqzq@sina.com
License: MIT
Platform: UNKNOWN
Requires-Python: >=3
